scu/__init__.py
scu/__main__.py
simple_commons_uploader-0.4.0.dist-info/LICENSE.md
simple_commons_uploader-0.4.0.dist-info/METADATA
simple_commons_uploader-0.4.0.dist-info/WHEEL
simple_commons_uploader-0.4.0.dist-info/entry_points.txt
simple_commons_uploader-0.4.0.dist-info/top_level.txt
simple_commons_uploader-0.4.0.dist-info/RECORD
