Metadata-Version: 2.1
Name: simple-commons-uploader
Version: 0.4.0
Summary: Batch Wikimedia Commons Uploader
Home-page: https://github.com/fastily/simple-commons-uploader
Author: Fastily
Author-email: fastily@users.noreply.github.com
Project-URL: Bug Tracker, https://github.com/fastily/simple-commons-uploader/issues
Classifier: Natural Language :: English
Classifier: Programming Language :: Python :: 3
Classifier: Programming Language :: Python :: 3.9
Classifier: License :: OSI Approved :: GNU General Public License v3 (GPLv3)
Classifier: Operating System :: OS Independent
Requires-Python: >=3.9
License-File: LICENSE.md
Requires-Dist: Pillow
Requires-Dist: pwiki
Requires-Dist: rich
